dap_py/__init__.py
dap_py/dap.py
dap_py/plot/__init__.py
dap_py/plot/plot.py
dap_py/utils/__init__.py
dap_py/utils/scraper.py
dap_py2/__init__.py
dap_py2/dap.py
dap_py2/plot/__init__.py
dap_py2/plot/plot.py
dap_py2/utils/__init__.py
dap_py2/utils/scraper.py
doe_dap_dl/__init__.py
doe_dap_dl/dap.py
doe_dap_dl/plot/__init__.py
doe_dap_dl/plot/plot.py
doe_dap_dl/utils/__init__.py
doe_dap_dl/utils/scraper.py
doe_dap_dl-0.5.0.dist-info/licenses/LICENSE.md
doe_dap_dl-0.5.0.dist-info/METADATA
doe_dap_dl-0.5.0.dist-info/WHEEL
doe_dap_dl-0.5.0.dist-info/top_level.txt
doe_dap_dl-0.5.0.dist-info/RECORD
